gameoflife_ndimage/__init__.py
gameoflife_ndimage/simulation.py
gameoflife_ndimage/video.py
gameoflife_ndimage-0.1.3.dist-info/LICENSE
gameoflife_ndimage-0.1.3.dist-info/WHEEL
gameoflife_ndimage-0.1.3.dist-info/METADATA
gameoflife_ndimage-0.1.3.dist-info/RECORD
