Metadata-Version: 2.1
Name: gameoflife-ndimage
Version: 0.1.3
Summary: Quick simulation of arbitrary rulesets for nearest-neighbour cellular automata. Uses scipy.ndimage.correlate, and can export videos via ffmpeg-python.
Home-page: https://github.com/RundownRhino/Cellular-Automata-Simulator
License: MIT
Keywords: gameoflife,cellular,automata,scipy
Author: RundownRhino
Author-email: 52856631+RundownRhino@users.noreply.github.com
Requires-Python: >=3.10,<4.0
Classifier: License :: OSI Approved :: MIT License
Classifier: Programming Language :: Python :: 3
Classifier: Programming Language :: Python :: 3.10
Classifier: Programming Language :: Python :: 3.11
Requires-Dist: ffmpeg-python (>=0.2.0,<0.3.0)
Requires-Dist: numpy (>=1.23.5,<2.0.0)
Requires-Dist: pillow (>=9.3.0,<10.0.0)
Requires-Dist: scipy (>=1.9.3,<2.0.0)
Project-URL: Repository, https://github.com/RundownRhino/Cellular-Automata-Simulator
